all_params_env/__init__.py
all_params_env/envs/__init__.py
all_params_env/envs/all_params_env.py
all_params_env/envs/curve_fit.py
all_params_env/envs/exp_1_basic_2i3c.py
all_params_env/envs/kinetic_modeling.py
all_params_env/envs/module_for_exp.py
all_params_env/envs/multiprocessing_env.py
all_params_env/opt_selfimple/__init__.py
all_params_env/opt_selfimple/deOpt.py
all_params_env/opt_selfimple/gaOpt.py
all_params_env/opt_selfimple/opt.py
all_params_env/opt_selfimple/pso.py
all_params_env/opt_selfimple/whaleOpt.py
all_params_env-0.0.1.dist-info/METADATA
all_params_env-0.0.1.dist-info/WHEEL
all_params_env-0.0.1.dist-info/top_level.txt
all_params_env-0.0.1.dist-info/RECORD
