Metadata-Version: 2.1
Name: all-params-env
Version: 0.0.1
Summary: A 0penAI Gym Env for Lsm
Home-page: UNKNOWN
License: UNKNOWN
Platform: UNKNOWN
Requires-Dist: gym
